{
  "content": "```json\n{\n  \"title\": \"The Magician's Apprentice\",\n  \"storyTitle\": \"The Magician's Secret\",\n  \"storySynopsis\": \"A young woman discovers she is the last surviving apprentice of a powerful but reclusive magician. Tasked with tracking down a mysterious artifact, she must unravel the secrets of her mentor's past while navigating a treacherous magical underworld. Along the way, she encounters allies, enemies, and the looming threat of a magical war breaking out. As she uncovers more about her mentor's legacy, she faces the ultimate test of her abilities and loyalty, with the fate of the magical world hanging in the balance.\",\n  \"storyTags\": [\"urban fantasy\", \"magic\", \"mystery\", \"adventure\", \"apprenticeship\", \"hidden legacy\", \"magical war\"],\n  \"content\": \"Chapter 1: The Apprentice's Journey\n\nThe air was thick with the scent of musty old books and the faint tang of burnt wood. Emma leaned against the door frame, taking in the sight of the cluttered workshop. Parchment scrolls were strewn across the floor, ancient tomes piled high on rickety shelves, and a faint glow emanated from a crystal orb perched on the desk. The room was a labyrinth of magical curiosities, each artifact whispering stories of a life lived in secrecy.\n\nEmma had always been drawn to the mysterious, but nothing could have prepared her for this. She had come here seeking answers, answers to questions that had haunted her since she was a child. Questions about her past, her family, and the strange dreams that felt more like memories. She had been searching for years, following cryptic clues and half-forgotten legends, until she finally found the name of the one person who could help her: the Magician.\n\nThe Magician was a legend in the magical community, known for his reclusiveness and his unparalleled skill in the arcane arts. He was a man of enigmatic power, his name whispered in hushed tones by those who knew of him. Many had tried to find him, to learn from him, but few succeeded. Emma was one of the few.\n\nShe had spent months tracking him down, piecing together fragments of information, following leads that led her to this small, unassuming shop in the heart of the city. The shop was unremarkable from the outside, blending in with the rest of the buildings on the street. But Emma knew better. She could feel the magic radiating from it, a subtle hum that told her she was in the right place.\n\nShe pushed the door open, the old bell above her head jingling softly. The Magician looked up from his work, his sharp eyes piercing through her. He was an imposing figure, tall and gaunt, with a mane of white hair that cascaded down his back. His face was lined with age, but his eyes sparkled with an ageless intelligence.\n\n“You seek answers,” he said, his voice deep and resonant. “But you must prove yourself worthy first.”\n\nEmma hesitated, unsure of what to say. She had expected a challenge, but she wasn't prepared for this. The Magician gestured to the mess around him, his eyes gleaming with amusement.\n\n“Find the artifact,” he commanded. “It is hidden here, somewhere in this room. Bring it to me, and you will earn your place as my apprentice.”\n\nEmma glanced around the room, her heart racing. The artifact could be anywhere. She started to search, her hands moving swiftly, her mind racing with possibilities. She sifted through the scrolls, ran her fingers along the spines of the tomes, and even peered into the orb, hoping for a clue.\n\nHours passed, and the room seemed to shift and change around her. The artifacts seemed to whisper to her, guiding her, whispering secrets. She felt the magic in the room, the ancient power that permeated every inch of the workshop. It was intoxicating, overwhelming.\n\nFinally, she found it. Tucked away in a hidden compartment at the back of an old chest, she found a small, ornate box. It was simple, almost plain, but she could feel the magic emanating from it. She picked it up, careful not to disturb the intricate carvings that adorned its surface.\n\n“I have it,” she said, turning to face the Magician.\n\nHe nodded, his eyes never leaving her. “Very well. You have passed the first test. But there will be more. Many more. Are you ready?”\n\nEmma took a deep breath, her mind racing with the possibilities that lay ahead. She had passed the first test, but she knew that the journey ahead would be long and difficult. She was ready for it, ready to embrace the secrets of the Magician, ready to become his apprentice.\n\nThe Magician's Secret had begun.\n\n# Chapter 1: The Magician's Secret\n\nThe air was thick with the scent of musty old books and the faint tang of burnt wood. Emma leaned against the door frame, taking in the sight of the cluttered workshop. Parchment scrolls were strewn across the floor, ancient tomes piled high on rickety shelves, and a faint glow emanated from a crystal orb perched on the desk. The room was a labyrinth of magical curiosities, each artifact whispering stories of a life lived in secrecy.\n\nEmma had always been drawn to the mysterious, but nothing could have prepared her for this. She had come here seeking answers, answers to questions that had haunted her since she was a child. Questions about her past, her family, and the strange dreams that felt more like memories. She had been searching for years, following cryptic clues and half-forgotten legends, until she finally found the name of the one person who could help her: the Magician.\n\nThe Magician was a legend in the magical community, known for his reclusiveness and his unparalleled skill in the arcane arts. He was a man of enigmatic power, his name whispered in hushed tones by those who knew of him. Many had tried to find him, to learn from him, but few succeeded. Emma was one of the few.\n\nShe had spent months tracking him down, piecing together fragments of information, following leads that led her to this small, unassuming shop in the heart of the city. The shop was unremarkable from the outside, blending in with the rest of the buildings on the street. But Emma knew better. She could feel the magic radiating from it, a subtle hum that told her she was in the right place.\n\nShe pushed the door open, the old bell above her head jingling softly. The Magician looked up from his work, his sharp eyes piercing through her. He was an imposing figure, tall and gaunt, with a mane of white hair that cascaded down his back. His face was lined with age, but his eyes sparkled with an ageless intelligence.\n\n“You seek answers,” he said, his voice deep and resonant. “But you must prove yourself worthy first.”\n\nEmma hesitated, unsure of what to say. She had expected a challenge, but she wasn't prepared for this. The Magician gestured to the mess around him, his eyes gleaming with amusement.\n\n“Find the artifact,” he commanded. “It is hidden here, somewhere in this room. Bring it to me, and you will earn your place as my apprentice.”\n\nEmma glanced around the room, her heart racing. The artifact could be anywhere. She started to search, her hands moving swiftly, her mind racing with possibilities. She sifted through the scrolls, ran her fingers along the spines of the tomes, and even peered into the orb, hoping for a clue.\n\nHours passed, and the room seemed to shift and change around her. The artifacts seemed to whisper to her, guiding her, whispering secrets. She felt the magic in the room, the ancient power that permeated every inch of the workshop. It was intoxicating, overwhelming.\n\nFinally, she found it. Tucked away in a hidden compartment at the back of an old chest, she found a small, ornate box. It was simple, almost plain, but she could feel the magic emanating from it. She picked it up, careful not to disturb the intricate carvings that adorned its surface.\n\n“I have it,” she said, turning to face the Magician.\n\nHe nodded, his eyes never leaving her. “Very well. You have passed the first test. But there will be more. Many more. Are you ready?”\n\nEmma took a deep breath, her mind racing with the possibilities that lay ahead. She had passed the first test, but she knew that the journey ahead would be long and difficult. She was ready for it, ready to embrace the secrets of the Magician, ready to become his apprentice.\n\nThe Magician's Secret had begun.\n\nChapter 2: The Artifact's Secrets\n\nEmma stood in the center of the workshop, the ornate box held tightly in her hands. The Magician watched her closely, his eyes never leaving her face. She could feel the weight of his expectations, the pressure to succeed.\n\n“Open it,” he said.\n\nEmma hesitated, the weight of the box suddenly feeling much heavier. She knew that whatever was inside was important, something that the Magician deemed worthy of being her test. Carefully, she placed the box on the desk and began to work the intricate lock.\n\nThe box clicked open, and Emma lifted the lid. Inside, nestled on a bed of soft velvet, was a small, ornate amulet. The amulet was beautiful, shimmering with an otherworldly light. It was unlike anything she had ever seen before, and she could feel the magic radiating from it.\n\n“This is the artifact,” the Magician said. “The key to everything. But it is not simply an object. It is a key to a door, a door that leads to a world of secrets.”\n\nEmma looked up at him, her mind racing with questions. “What secrets?” she asked.\n\nThe Magician smiled, a small, enigmatic smile that did nothing to ease her curiosity. “Secrets that you will discover in time,” he said. “But first, you must prove yourself. This is only the beginning.”\n\nEmma nodded, her heart racing. She knew that the journey ahead would be long and difficult, but she was ready for it. She was ready to embrace the secrets of the Magician, ready to become his apprentice.\n\nThe Magician's Secret had begun.\n\n# Chapter 2: The Artifact's Secrets\n\nEmma stood in the center of the workshop, the ornate box held tightly in her hands. The Magician watched her closely, his eyes never leaving her face. She could feel the weight of his expectations, the pressure to succeed.\n\n“Open it,” he said.\n\nEmma hesitated, the weight of the box suddenly feeling much heavier. She knew that whatever was inside was important, something that the Magician deemed worthy of being her test. Carefully, she placed the box on the desk and began to work the intricate lock.\n\nThe box clicked open, and Emma lifted the lid. Inside, nestled on a bed of soft velvet, was a small, ornate amulet. The amulet was beautiful, shimmering with an otherworldly light. It was unlike anything she had ever seen before, and she could feel the magic radiating from it.\n\n“This is the artifact,” the Magician said. “The key to everything. But it is not simply an object. It is a key to a door, a door that leads to a world of secrets.”\n\nEmma looked up at him, her mind racing with questions. “What secrets?” she asked.\n\nThe Magician smiled, a small, enigmatic smile that did nothing to ease her curiosity. “Secrets that you will discover in time,” he said. “But first, you must prove yourself. This is only the beginning.”\n\nEmma nodded, her heart racing. She knew that the journey ahead would be long and difficult, but she was ready for it. She was ready to embrace the secrets of the Magician, ready to become his apprentice.\n\nThe Magician's Secret had begun.\n\nChapter 3: The First Test\n\nEmma stood in the center of the workshop, the ornate box held tightly in her hands. The Magician watched her closely, his eyes never leaving her face. She could feel the weight of his expectations, the pressure to succeed.\n\n“Open it,” he said.\n\nEmma hesitated, the weight of the box suddenly feeling much heavier. She knew that whatever was inside was important, something that the Magician deemed worthy of being her test. Carefully, she placed the box on the desk and began to work the intricate lock.\n\nThe box clicked open, and Emma lifted the lid. Inside, nestled on a bed of soft velvet, was a small, ornate amulet. The amulet was beautiful, shimmering with an otherworldly light. It was unlike anything she had ever seen before, and she could feel the magic radiating from it.\n\n“This is the artifact,” the Magician said. “The key to everything. But it is not simply an object. It is a key to a door, a door that leads to a world of secrets.”\n\nEmma looked up at him, her mind racing with questions. “What secrets?” she asked.\n\nThe Magician smiled, a small, enigmatic smile that did nothing to ease her curiosity. “Secrets that you will discover in time,” he said. “But first, you must prove yourself. This is only the beginning.”\n\nEmma nodded, her heart racing. She knew that the journey ahead would be long and difficult, but she was ready for it. She was ready to embrace the secrets of the Magician, ready to become his apprentice.\n\nThe Magician's Secret had begun.\n\n# Chapter 3: The First Test\n\nEmma stood in the center of the workshop, the ornate box held tightly in her hands. The Magician watched her closely, his eyes never leaving her face. She could feel the weight of his expectations, the pressure to succeed.\n\n“Open it,” he said.\n\nEmma hesitated, the weight of the box suddenly feeling much heavier. She knew that whatever was inside was important, something that the Magician deemed worthy of being her test. Carefully, she placed the box on the desk and began to work the intricate lock.\n\nThe box clicked open, and Emma lifted the lid. Inside, nestled on a bed of soft velvet, was a small, ornate amulet. The amulet was beautiful, shimmering with an otherworldly light. It was unlike anything she had ever seen before, and she could feel the magic radiating from it.\n\n“This is the artifact,” the Magician said. “The key to everything. But it is not simply an object. It is a key to a door, a door that leads to a world of secrets.”\n\nEmma looked up at him, her mind racing with questions. “What secrets?” she asked.\n\nThe Magician smiled, a small, enigmatic smile that did nothing to ease her curiosity. “Secrets that you will discover in time,” he said. “But first, you must prove yourself. This is only the beginning.”\n\nEmma nodded, her heart racing. She knew that the journey ahead would be long and difficult, but she was ready for it. She was ready to embrace the secrets of the Magician, ready to become his apprentice.\n\nThe Magician's Secret had begun.\n\n# Chapter 4: The Journey Begins\n\nEmma stood in the center of the workshop, the ornate box held tightly in her hands. The Magician watched her closely, his eyes never leaving her face. She could feel the weight of his expectations, the pressure to succeed.\n\n“Open it,” he said.\n\nEmma hesitated, the weight of the box suddenly feeling much heavier. She knew that whatever was inside was important, something that the Magician deemed worthy of being her test. Carefully, she placed the box on the desk and began to work the intricate lock.\n\nThe box clicked open, and Emma lifted the lid. Inside, nestled on a bed of soft velvet, was a small, ornate amulet. The amulet was beautiful, shimmering with an otherworldly light. It was unlike anything she had ever seen before, and she could feel the magic radiating from it.\n\n“This is the artifact,” the Magician said. “The key to everything. But it is not simply an object. It is a key to a door, a door that leads to a world of secrets.”\n\nEmma looked up at him, her mind racing with questions. “What secrets?” she asked.\n\nThe Magician smiled, a small, enigmatic smile that did nothing to ease her curiosity. “Secrets that you will discover in time,” he said. “But first, you must prove yourself. This is only the beginning.”\n\nEmma nodded, her heart racing. She knew that the journey ahead would be long and difficult, but she was ready for it. She was ready to embrace the secrets of the Magician, ready to become his apprentice.\n\nThe Magician's Secret had begun.\n\n# Chapter 4: The Journey Begins\n\nEmma stood in the center of the workshop, the ornate box held tightly in her hands. The Magician watched her closely, his eyes never leaving her face. She could feel the weight of his expectations, the pressure to succeed.\n\n“Open it,” he said.\n\nEmma hesitated, the weight of the box suddenly feeling much heavier. She knew that whatever was inside was important, something that the Magician deemed worthy of being her test. Carefully, she placed the box on the desk and began to work the intricate lock.\n\nThe box clicked open, and Emma lifted the lid. Inside, nestled on a bed of soft velvet, was a small, ornate amulet. The amulet was beautiful, shimmering with an otherworldly light. It was unlike anything she had ever seen before, and she could feel the magic radiating from it.\n\n“This is the artifact,” the Magician said. “The key to everything. But it is not simply an object. It is a key to a door, a door that leads to a world of secrets.”\n\nEmma looked up at him, her mind racing with questions. “What secrets?” she asked.\n\nThe Magician smiled, a small, enigmatic smile that did nothing to ease her curiosity. “Secrets that you will discover in time,” he said. “But first, you must prove yourself. This is only the beginning.”\n\nEmma nodded, her heart racing. She knew that the journey ahead would be long and",
  "generatedAt": "2025-05-14T12:44:56.483Z"
}